getstream/__init__.py
getstream/base.py
getstream/config.py
getstream/generic.py
getstream/meta.py
getstream/rate_limit.py
getstream/stream.py
getstream/stream_response.py
getstream/version.py
getstream/chat/__init__.py
getstream/chat/async_channel.py
getstream/chat/async_client.py
getstream/chat/async_rest_client.py
getstream/chat/channel.py
getstream/chat/client.py
getstream/chat/rest_client.py
getstream/common/__init__.py
getstream/common/async_client.py
getstream/common/async_rest_client.py
getstream/common/client.py
getstream/common/rest_client.py
getstream/common/telemetry.py
getstream/feeds/__init__.py
getstream/feeds/client.py
getstream/feeds/feeds.py
getstream/feeds/rest_client.py
getstream/models/__init__.py
getstream/moderation/__init__.py
getstream/moderation/async_client.py
getstream/moderation/async_rest_client.py
getstream/moderation/client.py
getstream/moderation/rest_client.py
getstream/utils/__init__.py
getstream/utils/event_emitter.py
getstream/utils/retry.py
getstream/video/__init__.py
getstream/video/async_call.py
getstream/video/async_client.py
getstream/video/async_rest_client.py
getstream/video/call.py
getstream/video/client.py
getstream/video/openai.py
getstream/video/rest_client.py
getstream/video/rtc/README.md
getstream/video/rtc/__init__.py
getstream/video/rtc/audio_track.py
getstream/video/rtc/connection_manager.py
getstream/video/rtc/connection_utils.py
getstream/video/rtc/coordinator_api.py
getstream/video/rtc/g711.py
getstream/video/rtc/location_discovery.py
getstream/video/rtc/models.py
getstream/video/rtc/network_monitor.py
getstream/video/rtc/participants.py
getstream/video/rtc/pc.py
getstream/video/rtc/peer_connection.py
getstream/video/rtc/reconnection.py
getstream/video/rtc/recording.py
getstream/video/rtc/signaling.py
getstream/video/rtc/stats_reporter.py
getstream/video/rtc/stats_tracer.py
getstream/video/rtc/tracer.py
getstream/video/rtc/track_util.py
getstream/video/rtc/tracks.py
getstream/video/rtc/twirp_client_wrapper.py
getstream-2.7.1.dist-info/METADATA
getstream-2.7.1.dist-info/WHEEL
getstream-2.7.1.dist-info/licenses/LICENSE.md
getstream-2.7.1.dist-info/RECORD
