Metadata-Version: 2.4
Name: getstream
Version: 2.7.1
Summary: GetStream Python SDK - Build scalable activity feeds, chat, and video calling applications
Author-email: sachaarbonel <sacha.arbonel@hotmail.fr>, tbarbugli <tbarbugli@gmail.com>
License-File: LICENSE.md
Classifier: Programming Language :: Python :: 3
Classifier: Programming Language :: Python :: 3.9
Classifier: Programming Language :: Python :: 3.10
Classifier: Programming Language :: Python :: 3.11
Classifier: Programming Language :: Python :: 3.12
Classifier: Programming Language :: Python :: 3.13
Requires-Python: <4.0.0,>=3.10
Requires-Dist: dataclasses-json<0.7,>=0.6.0
Requires-Dist: httpx>=0.28.1
Requires-Dist: ijson>=3.4.0
Requires-Dist: marshmallow<4,>=3.21.0
Requires-Dist: protobuf>=6.31.1
Requires-Dist: pydantic-settings>=2.9.1
Requires-Dist: pydantic>=2.10.6
Requires-Dist: pyee>=13.0.0
Requires-Dist: pyjwt<3,>=2.8.0
Requires-Dist: python-dateutil>=2.8.2
Requires-Dist: twirp
Provides-Extra: openai-realtime
Requires-Dist: openai[realtime]>=1.93.0; extra == 'openai-realtime'
Provides-Extra: telemetry
Requires-Dist: opentelemetry-api>=1.26.0; extra == 'telemetry'
Requires-Dist: opentelemetry-sdk>=1.26.0; extra == 'telemetry'
Provides-Extra: webrtc
Requires-Dist: aiohttp<4,>=3.13.2; extra == 'webrtc'
Requires-Dist: aiortc-getstream==1.13.0.post1; extra == 'webrtc'
Requires-Dist: av<14.3,>=14.0.0; extra == 'webrtc'
Requires-Dist: numpy<2.3,>=2.2.6; extra == 'webrtc'
Requires-Dist: numpy>=2.2.6; extra == 'webrtc'
Requires-Dist: ping3>=4.0.8; extra == 'webrtc'
Requires-Dist: protobuf>=4.25.1; extra == 'webrtc'
Requires-Dist: protobuf>=6.31.1; extra == 'webrtc'
Requires-Dist: python-dateutil>=2.8.2; extra == 'webrtc'
Requires-Dist: scipy<1.16,>=1.15.3; extra == 'webrtc'
Requires-Dist: scipy>=1.15.3; extra == 'webrtc'
Requires-Dist: soundfile>=0.13.1; extra == 'webrtc'
Requires-Dist: structlog<24; extra == 'webrtc'
Requires-Dist: tenacity>=9.1.2; extra == 'webrtc'
Requires-Dist: twirp; extra == 'webrtc'
Requires-Dist: websocket-client>=1.8.0; extra == 'webrtc'
Requires-Dist: websockets<16,>=15.0.1; extra == 'webrtc'
Requires-Dist: websockets>=15.0.1; extra == 'webrtc'
